metabot2txt/__init__.py
metabot2txt/__main__.py
metabot2txt/convert.py
metabot2txt/display.py
metabot2txt-0.0.1.dist-info/LICENSE
metabot2txt-0.0.1.dist-info/METADATA
metabot2txt-0.0.1.dist-info/WHEEL
metabot2txt-0.0.1.dist-info/entry_points.txt
metabot2txt-0.0.1.dist-info/top_level.txt
metabot2txt-0.0.1.dist-info/RECORD
