Metadata-Version: 2.1
Name: metabot2txt
Version: 0.0.1
Summary: convert images of well structured tables to text
Home-page: https://github.com/HeitorBoschirolli/metabot2txt
Author: Heitor Boschirolli
Author-email: heitor.boschirolli@gmail.com
License: MIT
Platform: UNKNOWN
Classifier: License :: OSI Approved :: MIT License
Classifier: Programming Language :: Python :: 3
Classifier: Programming Language :: Python :: 3.6
Requires-Dist: pillow
Requires-Dist: pytesseract
Requires-Dist: scikit-image
